{"name":{"common":"South Georgia","official":"South Georgia and the South Sandwich Islands","native":{"eng":{"official":"South Georgia and the South Sandwich Islands","common":"South Georgia"}}},"demonym":"South Georgian South Sandwich Islander","capital":"King Edward Point","iso_3166_1_alpha2":"GS","iso_3166_1_alpha3":"SGS","iso_3166_1_numeric":"239","currency":{"GBP":{"iso_4217_code":"GBP","iso_4217_numeric":826,"iso_4217_name":"Pound sterling","iso_4217_minor_unit":2}},"tld":[".gs"],"alt_spellings":["GS","South Georgia and the South Sandwich Islands"],"languages":{"eng":"English"},"translations":{"deu":{"official":"Südgeorgien und die Südlichen Sandwichinseln","common":"Südgeorgien und die Südlichen Sandwichinseln"},"fra":{"official":"Géorgie du Sud et les îles Sandwich du Sud","common":"Géorgie du Sud-et-les Îles Sandwich du Sud"},"hrv":{"official":"Južna Džordžija i Otoci Južni Sendvič","common":"Južna Georgija i otočje Južni Sandwich"},"ita":{"official":"Georgia del Sud e isole Sandwich del Sud","common":"Georgia del Sud e Isole Sandwich Meridionali"},"jpn":{"official":"サウスジョージア·サウスサンドウィッチ諸島","common":"サウスジョージア・サウスサンドウィッチ諸島"},"nld":{"official":"Zuid-Georgië en de Zuidelijke Sandwich-eilanden","common":"Zuid-Georgia en Zuidelijke Sandwicheilanden"},"por":{"official":"Geórgia do Sul e Sandwich do Sul","common":"Ilhas Geórgia do Sul e Sandwich do Sul"},"rus":{"official":"Южная Георгия и Южные Сандвичевы острова","common":"Южная Георгия и Южные Сандвичевы острова"},"spa":{"official":"Georgia del Sur y las Islas Sandwich del Sur","common":"Islas Georgias del Sur y Sandwich del Sur"},"fin":{"official":"Etelä-Georgia ja Eteläiset Sandwichsaaret","common":"Etelä-Georgia ja Eteläiset Sandwichsaaret"}},"geo":{"continent":{"AN":"Antarctica"},"postal_code":true,"latitude":"54 30 S","latitude_dec":"-54.459922790527344","longitude":"37 00 W","longitude_dec":"-36.354618072509766","max_latitude":"-53.970278","max_longitude":"-26.333333","min_latitude":"-59.466667","min_longitude":"-38.305","area":3903,"region":"Americas","subregion":"South America","world_region":"AMER","region_code":"","subregion_code":"","landlocked":false,"borders":[],"independent":"Territory of GB"},"dialling":{"calling_code":["500"],"national_prefix":"","national_number_lengths":[],"national_destination_code_lengths":[],"international_prefix":""},"extra":{"geonameid":3474415,"edgar":0,"itu":0,"marc":"xs","wmo":0,"ds":0,"fifa":0,"fips":"SX","gaul":228,"ioc":0,"cowc":0,"cown":0,"fao":0,"imf":0,"ar5":"LAM","address_format":null,"eu_member":null,"vat_rates":null,"emoji":"🇬🇸"}}
